odoo/addons/edi_ubl_oca/README.rst
odoo/addons/edi_ubl_oca/__init__.py
odoo/addons/edi_ubl_oca/__manifest__.py
odoo/addons/edi_ubl_oca/data/edi_backend_type.xml
odoo/addons/edi_ubl_oca/demo/edi_backend_demo.xml
odoo/addons/edi_ubl_oca/i18n/edi_ubl_oca.pot
odoo/addons/edi_ubl_oca/i18n/it.po
odoo/addons/edi_ubl_oca/readme/CONTRIBUTORS.rst
odoo/addons/edi_ubl_oca/readme/DESCRIPTION.rst
odoo/addons/edi_ubl_oca/static/description/icon.png
odoo/addons/edi_ubl_oca/static/description/index.html
odoo14_addon_edi_ubl_oca-14.0.1.0.1.dev5.dist-info/METADATA
odoo14_addon_edi_ubl_oca-14.0.1.0.1.dev5.dist-info/WHEEL
odoo14_addon_edi_ubl_oca-14.0.1.0.1.dev5.dist-info/top_level.txt
odoo14_addon_edi_ubl_oca-14.0.1.0.1.dev5.dist-info/RECORD
